ipranges.py
ipranges-0.1.13.dist-info/LICENSE
ipranges-0.1.13.dist-info/METADATA
ipranges-0.1.13.dist-info/WHEEL
ipranges-0.1.13.dist-info/top_level.txt
ipranges-0.1.13.dist-info/zip-safe
ipranges-0.1.13.dist-info/RECORD
