Metadata-Version: 2.1
Name: ipranges
Version: 0.1.13
Summary: Python library for working with IP addressess.
Home-page: https://pypi.org/project/ipranges/
Author: Pavel Kacha
Author-email: pavel.kacha@cesnet.cz
License: ISC
Project-URL: Documentation, https://709.gitlab-pages.cesnet.cz/warden/ipranges/master/html/manual.html
Project-URL: Source, https://gitlab.cesnet.cz/709/warden/ipranges
Project-URL: Tracker, https://gitlab.cesnet.cz/709/warden/ipranges/-/issues
Keywords: library
Classifier: Development Status :: 4 - Beta
Classifier: License :: OSI Approved :: ISC License (ISCL)
Classifier: Programming Language :: Python
License-File: LICENSE
